phybers/__init__.py
phybers/clustering/__init__.py
phybers/clustering/clustering.py
phybers/clustering/ffclust/BundleTools.c
phybers/clustering/ffclust/__init__.py
phybers/clustering/ffclust/__main__.py
phybers/clustering/ffclust/bundleTools.h
phybers/clustering/ffclust/c_wrappers.c
phybers/clustering/ffclust/c_wrappers.cp39-win_amd64.pyd
phybers/clustering/ffclust/clustering.py
phybers/clustering/ffclust/metric.py
phybers/clustering/ffclust/processing.py
phybers/clustering/ffclust/segmentation.c
phybers/clustering/ffclust/segmentation.h
phybers/clustering/ffclust/utils.py
phybers/clustering/hclust/BundleTools.cpp
phybers/clustering/hclust/__init__.py
phybers/clustering/hclust/__main__.py
phybers/clustering/hclust/bundleTools.hpp
phybers/clustering/hclust/c_wrappers.cp39-win_amd64.pyd
phybers/clustering/hclust/c_wrappers.cpp
phybers/clustering/hclust/clusterTools.py
phybers/clustering/hclust/distances.cpp
phybers/clustering/hclust/distances.hpp
phybers/clustering/hclust/read_write_bundle.py
phybers/fibervis/FiberVis.py
phybers/fibervis/GLContext.py
phybers/fibervis/WindowController.py
phybers/fibervis/__init__.py
phybers/fibervis/__main__.py
phybers/fibervis/FiberVis_core/AtlasBasedParallelSegmentation.c
phybers/fibervis/FiberVis_core/AtlasBasedParallelSegmentation.h
phybers/fibervis/FiberVis_core/FiberVis_core.c
phybers/fibervis/FiberVis_core/FiberVis_core.cp39-win_amd64.pyd
phybers/fibervis/FiberVis_core/InPlaceSegmentationMethod.h
phybers/fibervis/FiberVis_core/PointOctree.c
phybers/fibervis/FiberVis_core/PointOctree.h
phybers/fibervis/FiberVis_core/__init__.py
phybers/fibervis/FiberVis_core/bundleMethods.c
phybers/fibervis/FiberVis_core/bundleMethods.h
phybers/fibervis/FiberVis_core/ffclust.c
phybers/fibervis/FiberVis_core/ffclust.h
phybers/fibervis/FiberVis_core/functions.h
phybers/fibervis/FiberVis_core/miscellaneous.c
phybers/fibervis/FiberVis_core/miscellaneous.h
phybers/fibervis/Framework/BoundingBox.py
phybers/fibervis/Framework/Bundle.py
phybers-1.1.2.dist-info/METADATA
phybers-1.1.2.dist-info/WHEEL
phybers-1.1.2.dist-info/entry_points.txt
phybers-1.1.2.dist-info/top_level.txt
phybers-1.1.2.dist-info/RECORD
