Metadata-Version: 2.1
Name: phybers
Version: 1.1.2
Summary: Phybers: A Package for Brain Tractography Analysis.
Home-page: https://github.com/phybers/phybers
Author: L. Liset Gonzalez, Alejandro Cofre
Author-email: phybers.dmris@gmail.com
License: GNU
Requires-Dist: numpy
Requires-Dist: dipy
Requires-Dist: joblib
Requires-Dist: matplotlib
Requires-Dist: scikit-learn
Requires-Dist: networkx
Requires-Dist: pandas
Requires-Dist: PyQt5
Requires-Dist: PyOpenGL
Requires-Dist: PyOpenGL-accelerate
Requires-Dist: nibabel
Requires-Dist: pydicom
Requires-Dist: scikit-image
Requires-Dist: scipy
Requires-Dist: openpyxl
Requires-Dist: regex
Requires-Dist: importlib-resources
